{
  "view": {
    "type": "data_series",
    "range": [
      {
        "label": "Total de policiais civis",
        "value": "quantidade_pessoas_sum"
      }
    ],
    "domain": "genero",
    "filterBy": [
      {
        "type": "single",
        "variableId": "ano"
      }
    ],
    "chartType": "bars",
    "defaultValues": {
      "filterBy": {
        "ano": 2023
      }
    },
    "dataSourceType": "aggregation",
    "filterByStateId": "sigla_uf"
  },
  "variables": {
    "ano": {
      "type": "continuous",
      "label": "Ano",
      "options": [
        2019,
        2023
      ],
      "variableId": "ano",
      "phrasePrefix": "no ano de"
    },
    "genero": {
      "type": "categorical",
      "label": "Gênero",
      "options": [
        {
          "color": "dark-blue",
          "label": "Feminino",
          "value": "Feminino"
        },
        {
          "color": "green",
          "label": "Masculino",
          "value": "Masculino"
        }
      ],
      "phrasePrefix": "do sexo"
    },
    "sigla_uf": {
      "type": "categorical",
      "label": "UF",
      "options": [
        "IGNORADO",
        "AC",
        "AL",
        "AM",
        "AP",
        "BA",
        "CE",
        "DF",
        "ES",
        "GO",
        "MA",
        "MG",
        "MS",
        "MT",
        "PA",
        "PB",
        "PE",
        "PI",
        "PR",
        "RJ",
        "RN",
        "RO",
        "RR",
        "RS",
        "SC",
        "SE",
        "SP",
        "TO"
      ]
    },
    "quantidade_pessoas": {
      "type": "continuous",
      "label": "Quantidade de pessoas"
    }
  }
}